Metadata-Version: 2.1
Name: trgm
Version: 0.0.1
Summary: A library to help you create text adventure games with Python
Home-page: https://github.com/your_username/my_library
Author: Nithil Gadde
Author-email: nithilgadde2010@gmail.com
Classifier: Programming Language :: Python :: 3
Classifier: License :: OSI Approved :: MIT License
Classifier: Operating System :: OS Independent
